odoo/addons/rma_sale_lot/README.rst
odoo/addons/rma_sale_lot/__init__.py
odoo/addons/rma_sale_lot/__manifest__.py
odoo/addons/rma_sale_lot/i18n/it.po
odoo/addons/rma_sale_lot/i18n/rma_sale_lot.pot
odoo/addons/rma_sale_lot/models/__init__.py
odoo/addons/rma_sale_lot/models/sale_order.py
odoo/addons/rma_sale_lot/models/sale_order_line.py
odoo/addons/rma_sale_lot/readme/CONTRIBUTORS.md
odoo/addons/rma_sale_lot/readme/DESCRIPTION.md
odoo/addons/rma_sale_lot/static/description/icon.png
odoo/addons/rma_sale_lot/static/description/index.html
odoo/addons/rma_sale_lot/tests/__init__.py
odoo/addons/rma_sale_lot/tests/test_rma_sale_lot.py
odoo/addons/rma_sale_lot/wizards/__init__.py
odoo/addons/rma_sale_lot/wizards/sale_order_line_rma_wizard.py
odoo/addons/rma_sale_lot/wizards/sale_order_rma_wizard.xml
odoo_addon_rma_sale_lot-16.0.1.0.0.4.dist-info/METADATA
odoo_addon_rma_sale_lot-16.0.1.0.0.4.dist-info/WHEEL
odoo_addon_rma_sale_lot-16.0.1.0.0.4.dist-info/top_level.txt
odoo_addon_rma_sale_lot-16.0.1.0.0.4.dist-info/RECORD
