Metadata-Version: 2.1
Name: odoo-addon-rma_sale_lot
Version: 16.0.1.0.0.4
Summary: Manage sale returns with lot.
Home-page: https://github.com/OCA/rma
Author: ACSONE SA/NV,BCIM,Odoo Community Association (OCA)
Author-email: support@odoo-community.org
License: AGPL-3
Classifier: Programming Language :: Python
Classifier: Framework :: Odoo
Classifier: Framework :: Odoo :: 16.0
Classifier: License :: OSI Approved :: GNU Affero General Public License v3
Requires-Python: >=3.10
Requires-Dist: odoo-addon-rma-lot<16.1dev,>=16.0dev
Requires-Dist: odoo-addon-rma-sale<16.1dev,>=16.0dev
Requires-Dist: odoo<16.1dev,>=16.0a
